kiclearance/__init__.py
kiclearance/__main__.py
kiclearance/kiclearance.py
kiclearance-0.2.1.dist-info/METADATA
kiclearance-0.2.1.dist-info/WHEEL
kiclearance-0.2.1.dist-info/RECORD
