Metadata-Version: 2.4
Name: kiclearance
Version: 0.2.1
Summary: Generate clearance rules for KiCAD by a table.
Project-URL: Homepage, https://github.com/upb-lea/kiclearance
Project-URL: Issues, https://github.com/upb-lea/kiclearance/issues
Author: UPB-LEA
Classifier: License :: OSI Approved :: MIT License
Classifier: Operating System :: OS Independent
Classifier: Programming Language :: Python :: 3
Requires-Python: >=3.10
Requires-Dist: numpy
Requires-Dist: odfpy
Requires-Dist: openpyxl
Requires-Dist: pandas
Requires-Dist: pyyaml
